chainmodel/__init__.py
chainmodel/chainmodel.py
chainmodel/models/__init__.py
chainmodel/models/base/__init__.py
chainmodel/models/base/operation.py
chainmodel/models/steem/__init__.py
chainmodel/models/steem/block.py
chainmodel/models/steem/operation.py
chainmodel/models/steem/schema.py
chainmodel/models/steem/ops/__init__.py
chainmodel/models/steem/ops/account_create.py
chainmodel/models/steem/ops/account_create_with_delegation.py
chainmodel/models/steem/ops/account_update.py
chainmodel/models/steem/ops/account_witness_proxy.py
chainmodel/models/steem/ops/account_witness_vote.py
chainmodel/models/steem/ops/author_reward.py
chainmodel/models/steem/ops/cancel_transfer_from_savings.py
chainmodel/models/steem/ops/change_recovery_account.py
chainmodel/models/steem/ops/claim_reward_balance.py
chainmodel/models/steem/ops/comment.py
chainmodel/models/steem/ops/comment_benefactor_reward.py
chainmodel/models/steem/ops/comment_options.py
chainmodel/models/steem/ops/convert.py
chainmodel/models/steem/ops/curation_reward.py
chainmodel/models/steem/ops/custom.py
chainmodel/models/steem/ops/custom_json.py
chainmodel/models/steem/ops/decline_voting_rights.py
chainmodel/models/steem/ops/delegate_vesting_shares.py
chainmodel/models/steem/ops/delete_comment.py
chainmodel/models/steem/ops/escrow_approve.py
chainmodel/models/steem/ops/escrow_dispute.py
chainmodel/models/steem/ops/escrow_release.py
chainmodel/models/steem/ops/escrow_transfer.py
chainmodel/models/steem/ops/feed_publish.py
chainmodel/models/steem/ops/fill_convert_request.py
chainmodel/models/steem/ops/fill_order.py
chainmodel/models/steem/ops/fill_transfer_from_savings.py
chainmodel/models/steem/ops/fill_vesting_withdraw.py
chainmodel/models/steem/ops/follow.py
chainmodel/models/steem/ops/interest.py
chainmodel/models/steem/ops/limit_order_cancel.py
chainmodel/models/steem/ops/limit_order_create.py
chainmodel/models/steem/ops/limit_order_create2.py
chainmodel-0.1.3.dist-info/DESCRIPTION.rst
chainmodel-0.1.3.dist-info/METADATA
chainmodel-0.1.3.dist-info/RECORD
chainmodel-0.1.3.dist-info/WHEEL
chainmodel-0.1.3.dist-info/metadata.json
chainmodel-0.1.3.dist-info/top_level.txt
