Metadata-Version: 2.0
Name: chainmodel
Version: 0.1.3
Summary: Provides a layer for interpretting and transforming block and op data
Home-page: http://github.com/aaroncox/chainmodel
Author: Aaron Cox
Author-email: aaron@greymass.com
License: MIT
Platform: UNKNOWN
